iap_auth/__init__.py
iap_auth/iap_client.py
iap_auth/user_client.py
iap_auth/util.py
iap_auth-0.2.2.dist-info/METADATA
iap_auth-0.2.2.dist-info/WHEEL
iap_auth-0.2.2.dist-info/top_level.txt
iap_auth-0.2.2.dist-info/RECORD
