Metadata-Version: 2.1
Name: iap-auth
Version: 0.2.2
Summary: Performs authentication for Google Cloud Identity Aware Proxy from a service account
Home-page: https://github.com/lmtani/iap-auth
Author: Lucas Taniguti
Author-email: ltaniguti@gmail.com
License: unlicense
Platform: UNKNOWN
Requires-Dist: google-auth
Requires-Dist: requests
